LICENSE.txt
MANIFEST.in
README.rst
setup.py
tw2/__init__.py
tw2.bootstrap.forms.egg-info/PKG-INFO
tw2.bootstrap.forms.egg-info/SOURCES.txt
tw2.bootstrap.forms.egg-info/dependency_links.txt
tw2.bootstrap.forms.egg-info/entry_points.txt
tw2.bootstrap.forms.egg-info/namespace_packages.txt
tw2.bootstrap.forms.egg-info/not-zip-safe
tw2.bootstrap.forms.egg-info/requires.txt
tw2.bootstrap.forms.egg-info/top_level.txt
tw2/bootstrap/__init__.py
tw2/bootstrap/forms/__init__.py
tw2/bootstrap/forms/calendars.py
tw2/bootstrap/forms/samples.py
tw2/bootstrap/forms/widgets.py
tw2/bootstrap/forms/static/bootstrap-datetimepicker.css
tw2/bootstrap/forms/static/bootstrap-datetimepicker.js
tw2/bootstrap/forms/static/bootstrap-datetimepicker.min.js
tw2/bootstrap/forms/static/bootstrap/css/bootstrap-responsive.css
tw2/bootstrap/forms/static/bootstrap/css/bootstrap-responsive.min.css
tw2/bootstrap/forms/static/bootstrap/css/bootstrap.css
tw2/bootstrap/forms/static/bootstrap/css/bootstrap.min.css
tw2/bootstrap/forms/static/bootstrap/img/glyphicons-halflings-white.png
tw2/bootstrap/forms/static/bootstrap/img/glyphicons-halflings.png
tw2/bootstrap/forms/static/bootstrap/js/bootstrap.js
tw2/bootstrap/forms/static/bootstrap/js/bootstrap.min.js
tw2/bootstrap/forms/static/datepicker/css/datepicker.css
tw2/bootstrap/forms/static/datepicker/js/bootstrap-datepicker.js
tw2/bootstrap/forms/static/datepicker/less/datepicker.less
tw2/bootstrap/forms/static/timepicker/.gitignore
tw2/bootstrap/forms/static/timepicker/README.md
tw2/bootstrap/forms/static/timepicker/css/timepicker.css
tw2/bootstrap/forms/static/timepicker/js/bootstrap-timepicker.js
tw2/bootstrap/forms/static/timepicker/less/timepicker.less
tw2/bootstrap/forms/templates/__init__.py
tw2/bootstrap/forms/templates/__init__.pyc
tw2/bootstrap/forms/templates/bool_control.mak
tw2/bootstrap/forms/templates/datepicker.mak
tw2/bootstrap/forms/templates/datetimepicker.mak
tw2/bootstrap/forms/templates/horizontal_form.mak
tw2/bootstrap/forms/templates/horizontal_layout.mak
tw2/bootstrap/forms/templates/inline_layout.mak
tw2/bootstrap/forms/templates/label_field.mak
tw2/bootstrap/forms/templates/selection_list.mak
tw2/bootstrap/forms/templates/selection_table.mak
tw2/bootstrap/forms/templates/spacer.mak
tw2/bootstrap/forms/templates/vertical_selection_table.mak