Metadata-Version: 1.1
Name: tw2.bootstrap.forms
Version: 2.2.0
Summary: A drop-in replacement for tw2.forms but with bootstrap!
Home-page: http://github.com/toscawidgets/tw2.bootstrap
Author: Moritz Schlarb, Ralph Bean
Author-email: moschlar@metalabs.de, rbean@redhat.com
License: BSD 2-clause
Keywords: toscawidgets.widgets
Platform: UNKNOWN
Classifier: Development Status :: 3 - Alpha
Classifier: Environment :: Web Environment
Classifier: Environment :: Web Environment :: ToscaWidgets
Classifier: Topic :: Software Development :: Libraries :: Python Modules
Classifier: Topic :: Software Development :: Widget Sets
Classifier: Intended Audience :: Developers
Classifier: Operating System :: OS Independent
Classifier: Programming Language :: Python
Classifier: License :: OSI Approved :: BSD License
